regression_model/VERSION
regression_model/__init__.py
regression_model/config.yml
regression_model/pipeline.py
regression_model/predict.py
regression_model/train_pipeline.py
regression_model/config/__init__.py
regression_model/config/core.py
regression_model/datasets/__init__.py
regression_model/datasets/data.csv
regression_model/datasets/new_data.csv
regression_model/processing/__init__.py
regression_model/processing/data_manager.py
regression_model/processing/datapreprocessor.py
regression_model/processing/sklearn_preprocessors.py
regression_model/processing/validation.py
regression_model/trained_models/__init__.py
regression_model/trained_models/regression_model_output_v0.0.4.pkl
lasso_regression_model-0.0.4.dist-info/LICENSE
lasso_regression_model-0.0.4.dist-info/METADATA
lasso_regression_model-0.0.4.dist-info/WHEEL
lasso_regression_model-0.0.4.dist-info/top_level.txt
lasso_regression_model-0.0.4.dist-info/RECORD
