Metadata-Version: 2.1
Name: lasso-regression-model
Version: 0.0.4
Summary: Lasso Regression model package
Home-page: https://github.com/mm-mazhar/Deploying-ML-Lasso-Regression-Model
Author: Mazhar
Author-email: Mazhar <mazqoty.01@gmail.com>
License: Copyright (c) 2018 The Python Packaging Authority
Project-URL: Homepage, https://github.com/mm-mazhar/Deploying-ML-Lasso-Regression-Model
Project-URL: Bug Tracker, https://github.com/mm-mazhar/Deploying-ML-Lasso-Regression-Model/issues
Classifier: Programming Language :: Python :: 3
Classifier: License :: OSI Approved :: MIT License
Requires-Python: >=3.6.0
License-File: LICENSE
Requires-Dist: numpy <1.25.3,>=1.24.3
Requires-Dist: pandas ==1.5.3
Requires-Dist: pydantic <2.0.0,>=1.8.1
Requires-Dist: scikit-learn <1.3.2,>=1.2.2
Requires-Dist: strictyaml <2.0.0,>=1.3.2
Requires-Dist: ruamel.yaml <1.0.0,>=0.16.12
Requires-Dist: feature-engine <1.7.0,>=1.6.0
Requires-Dist: joblib <1.3.0,>=1.2.0
Requires-Dist: scipy <1.11.0,>=1.10.1
Requires-Dist: seaborn <0.13.0,>=0.12.1
Requires-Dist: matplotlib <3.8.0,>=3.7.1
Requires-Dist: statsmodels <0.14.0,>=0.13.5
Requires-Dist: twine
Requires-Dist: pytest <8.0.0,>=7.2.0
Requires-Dist: black <23.0.0,>=22.12.0
Requires-Dist: flake8 <7.0.0,>=6.0.0
Requires-Dist: mypy <1.0.0,>=0.991
Requires-Dist: isort <6.0.0,>=5.11.4
